shoveboxlist/__init__.py
shoveboxlist/apps.py
shoveboxlist/forms.py
shoveboxlist/renderers.py
shoveboxlist/tests.py
shoveboxlist/views.py
shoveboxlist/widgets.py
shoveboxlist/static/shoveboxlist/css/context-menu.css
shoveboxlist/static/shoveboxlist/css/shoveboxlist.css
shoveboxlist/static/shoveboxlist/images/delete.png
shoveboxlist/static/shoveboxlist/js/context-menu.js
shoveboxlist/static/shoveboxlist/js/shoveboxlist.js
shoveboxlist/templates/shoveboxlist/shovebox.html
shoveboxlist/templates/shoveboxlist/widgets/deletecheckbox.html
shoveboxlist/templates/shoveboxlist/widgets/levelslider.html
shoveboxlist/templates/shoveboxlist/widgets/sbformulainput.html
shoveboxlist/templates/shoveboxlist/widgets/sbnumberinput.html
shoveboxlist/templates/shoveboxlist/widgets/sbref.html
shoveboxlist/templates/shoveboxlist/widgets/sbselect.html
shoveboxlist/templates/shoveboxlist/widgets/sbshrinkabletextinput.html
shoveboxlist/templates/shoveboxlist/widgets/sbtextinput.html
shoveboxlist/templates/shoveboxlist/widgets/typeswitch.html
django_shoveboxlist-0.9.2.dist-info/LICENSE
django_shoveboxlist-0.9.2.dist-info/METADATA
django_shoveboxlist-0.9.2.dist-info/WHEEL
django_shoveboxlist-0.9.2.dist-info/top_level.txt
django_shoveboxlist-0.9.2.dist-info/RECORD
